hses3operations_pkg/__init__.py
hses3operations_pkg/hses3operations.py
hses3operations_pkg_paulhyndman1969-0.0.1.dist-info/METADATA
hses3operations_pkg_paulhyndman1969-0.0.1.dist-info/WHEEL
hses3operations_pkg_paulhyndman1969-0.0.1.dist-info/top_level.txt
hses3operations_pkg_paulhyndman1969-0.0.1.dist-info/RECORD
