Metadata-Version: 2.1
Name: hses3operations-pkg-paulhyndman1969
Version: 0.0.1
Summary: HSE S3 Operations
Home-page: https://github.com/PaulHyndman
Author: Paul Hyndman
Author-email: paulhyndman@email.com
License: UNKNOWN
Platform: UNKNOWN
Classifier: Programming Language :: Python :: 3
Classifier: License :: OSI Approved :: MIT License
Classifier: Operating System :: OS Independent
Requires-Python: >=3.6
